{
    "Version": "1.2",
    "Data": {
        "Source": "d:\\palworldsdk\\plugins\\wwise\\intermediate\\build\\win64\\unrealeditor\\development\\akaudio\\module.akaudio.8_of_9.cpp",
        "ProvidedModule": "",
        "PCH": "d:\\palworldsdk\\intermediate\\build\\win64\\paleditor\\development\\unrealed\\sharedpch.unrealed.shadowerrors.h.pch",
        "Includes": [
            "d:\\palworldsdk\\plugins\\wwise\\intermediate\\build\\win64\\unrealeditor\\development\\akaudio\\definitions.akaudio.h",
            "d:\\palworldsdk\\plugins\\wwise\\source\\akaudio\\private\\akmediaasset.cpp",
            "d:\\palworldsdk\\plugins\\wwise\\source\\akaudio\\classes\\akmediaasset.h",
            "d:\\palworldsdk\\plugins\\wwise\\source\\akaudio\\classes\\akuefeatures.h",
            "d:\\palworldsdk\\plugins\\wwise\\thirdparty\\include\\ak\\akwwisesdkversion.h",
            "d:\\palworldsdk\\plugins\\wwise\\intermediate\\build\\win64\\unrealeditor\\inc\\akaudio\\uht\\akmediaasset.generated.h",
            "d:\\palworldsdk\\plugins\\wwise\\source\\akaudio\\public\\akaudiodevice.h",
            "d:\\palworldsdk\\plugins\\wwise\\source\\akaudio\\public\\akinclude.h",
            "d:\\ue_5.1\\engine\\source\\runtime\\core\\public\\windows\\allowwindowsplatformtypes.h",
            "d:\\ue_5.1\\engine\\source\\runtime\\core\\public\\windows\\windowshwrapper.h",
            "d:\\ue_5.1\\engine\\source\\runtime\\core\\public\\windows\\prewindowsapi.h",
            "d:\\ue_5.1\\engine\\source\\runtime\\core\\public\\windows\\minwindows.h",
            "c:\\program files (x86)\\windows kits\\10\\include\\10.0.22621.0\\um\\windows.h",
            "c:\\program files (x86)\\windows kits\\10\\include\\10.0.22621.0\\shared\\sdkddkver.h",
            "c:\\program files\\microsoft visual studio\\2022\\community\\vc\\tools\\msvc\\14.33.31629\\include\\excpt.h",
            "c:\\program files (x86)\\windows kits\\10\\include\\10.0.22621.0\\shared\\windef.h",
            "c:\\program files (x86)\\windows kits\\10\\include\\10.0.22621.0\\shared\\minwindef.h",
            "c:\\program files (x86)\\windows kits\\10\\include\\10.0.22621.0\\um\\winnt.h",
            "c:\\program files (x86)\\windows kits\\10\\include\\10.0.22621.0\\shared\\kernelspecs.h",
            "c:\\program files (x86)\\windows kits\\10\\include\\10.0.22621.0\\shared\\basetsd.h",
            "c:\\program files (x86)\\windows kits\\10\\include\\10.0.22621.0\\shared\\guiddef.h",
            "c:\\program files (x86)\\windows kits\\10\\include\\10.0.22621.0\\shared\\pshpack4.h",
            "c:\\program files (x86)\\windows kits\\10\\include\\10.0.22621.0\\shared\\poppack.h",
            "c:\\program files (x86)\\windows kits\\10\\include\\10.0.22621.0\\shared\\pshpack4.h",
            "c:\\program files (x86)\\windows kits\\10\\include\\10.0.22621.0\\shared\\poppack.h",
            "c:\\program files (x86)\\windows kits\\10\\include\\10.0.22621.0\\shared\\pshpack4.h",
            "c:\\program files (x86)\\windows kits\\10\\include\\10.0.22621.0\\shared\\pshpack2.h",
            "c:\\program files (x86)\\windows kits\\10\\include\\10.0.22621.0\\shared\\poppack.h",
            "c:\\program files (x86)\\windows kits\\10\\include\\10.0.22621.0\\shared\\pshpack2.h",
            "c:\\program files (x86)\\windows kits\\10\\include\\10.0.22621.0\\shared\\pshpack2.h",
            "c:\\program files (x86)\\windows kits\\10\\include\\10.0.22621.0\\shared\\poppack.h",
            "c:\\program files (x86)\\windows kits\\10\\include\\10.0.22621.0\\shared\\poppack.h",
            "c:\\program files (x86)\\windows kits\\10\\include\\10.0.22621.0\\shared\\pshpack8.h",
            "c:\\program files (x86)\\windows kits\\10\\include\\10.0.22621.0\\shared\\poppack.h",
            "c:\\program files (x86)\\windows kits\\10\\include\\10.0.22621.0\\shared\\pshpack1.h",
            "c:\\program files (x86)\\windows kits\\10\\include\\10.0.22621.0\\shared\\poppack.h",
            "c:\\program files (x86)\\windows kits\\10\\include\\10.0.22621.0\\shared\\pshpack1.h",
            "c:\\program files (x86)\\windows kits\\10\\include\\10.0.22621.0\\shared\\poppack.h",
            "c:\\program files (x86)\\windows kits\\10\\include\\10.0.22621.0\\shared\\poppack.h",
            "c:\\program files (x86)\\windows kits\\10\\include\\10.0.22621.0\\shared\\apiset.h",
            "c:\\program files (x86)\\windows kits\\10\\include\\10.0.22621.0\\shared\\ktmtypes.h",
            "c:\\program files (x86)\\windows kits\\10\\include\\10.0.22621.0\\um\\winbase.h",
            "c:\\program files (x86)\\windows kits\\10\\include\\10.0.22621.0\\shared\\apisetcconv.h",
            "c:\\program files (x86)\\windows kits\\10\\include\\10.0.22621.0\\um\\minwinbase.h",
            "c:\\program files (x86)\\windows kits\\10\\include\\10.0.22621.0\\um\\apiquery2.h",
            "c:\\program files (x86)\\windows kits\\10\\include\\10.0.22621.0\\um\\processenv.h",
            "c:\\program files (x86)\\windows kits\\10\\include\\10.0.22621.0\\um\\fileapifromapp.h",
            "c:\\program files (x86)\\windows kits\\10\\include\\10.0.22621.0\\um\\fileapi.h",
            "c:\\program files (x86)\\windows kits\\10\\include\\10.0.22621.0\\um\\debugapi.h",
            "c:\\program files (x86)\\windows kits\\10\\include\\10.0.22621.0\\um\\utilapiset.h",
            "c:\\program files (x86)\\windows kits\\10\\include\\10.0.22621.0\\um\\handleapi.h",
            "c:\\program files (x86)\\windows kits\\10\\include\\10.0.22621.0\\um\\errhandlingapi.h",
            "c:\\program files (x86)\\windows kits\\10\\include\\10.0.22621.0\\um\\fibersapi.h",
            "c:\\program files (x86)\\windows kits\\10\\include\\10.0.22621.0\\um\\namedpipeapi.h",
            "c:\\program files (x86)\\windows kits\\10\\include\\10.0.22621.0\\um\\profileapi.h",
            "c:\\program files (x86)\\windows kits\\10\\include\\10.0.22621.0\\um\\heapapi.h",
            "c:\\program files (x86)\\windows kits\\10\\include\\10.0.22621.0\\um\\ioapiset.h",
            "c:\\program files (x86)\\windows kits\\10\\include\\10.0.22621.0\\um\\synchapi.h",
            "c:\\program files (x86)\\windows kits\\10\\include\\10.0.22621.0\\um\\interlockedapi.h",
            "c:\\program files (x86)\\windows kits\\10\\include\\10.0.22621.0\\um\\processthreadsapi.h",
            "c:\\program files (x86)\\windows kits\\10\\include\\10.0.22621.0\\um\\sysinfoapi.h",
            "c:\\program files (x86)\\windows kits\\10\\include\\10.0.22621.0\\um\\memoryapi.h",
            "c:\\program files (x86)\\windows kits\\10\\include\\10.0.22621.0\\um\\enclaveapi.h",
            "c:\\program files (x86)\\windows kits\\10\\include\\10.0.22621.0\\um\\threadpoollegacyapiset.h",
            "c:\\program files (x86)\\windows kits\\10\\include\\10.0.22621.0\\um\\threadpoolapiset.h",
            "c:\\program files (x86)\\windows kits\\10\\include\\10.0.22621.0\\um\\jobapi.h",
            "c:\\program files (x86)\\windows kits\\10\\include\\10.0.22621.0\\um\\jobapi2.h",
            "c:\\program files (x86)\\windows kits\\10\\include\\10.0.22621.0\\um\\wow64apiset.h",
            "c:\\program files (x86)\\windows kits\\10\\include\\10.0.22621.0\\um\\libloaderapi.h",
            "c:\\program files (x86)\\windows kits\\10\\include\\10.0.22621.0\\um\\securitybaseapi.h",
            "c:\\program files (x86)\\windows kits\\10\\include\\10.0.22621.0\\um\\namespaceapi.h",
            "c:\\program files (x86)\\windows kits\\10\\include\\10.0.22621.0\\um\\systemtopologyapi.h",
            "c:\\program files (x86)\\windows kits\\10\\include\\10.0.22621.0\\um\\processtopologyapi.h",
            "c:\\program files (x86)\\windows kits\\10\\include\\10.0.22621.0\\um\\securityappcontainer.h",
            "c:\\program files (x86)\\windows kits\\10\\include\\10.0.22621.0\\um\\realtimeapiset.h",
            "c:\\program files (x86)\\windows kits\\10\\include\\10.0.22621.0\\shared\\winerror.h",
            "c:\\program files (x86)\\windows kits\\10\\include\\10.0.22621.0\\um\\timezoneapi.h",
            "c:\\program files (x86)\\windows kits\\10\\include\\10.0.22621.0\\um\\wingdi.h",
            "c:\\program files (x86)\\windows kits\\10\\include\\10.0.22621.0\\shared\\pshpack1.h",
            "c:\\program files (x86)\\windows kits\\10\\include\\10.0.22621.0\\shared\\poppack.h",
            "c:\\program files (x86)\\windows kits\\10\\include\\10.0.22621.0\\shared\\pshpack2.h",
            "c:\\program files (x86)\\windows kits\\10\\include\\10.0.22621.0\\shared\\poppack.h",
            "c:\\program files (x86)\\windows kits\\10\\include\\10.0.22621.0\\shared\\pshpack4.h",
            "c:\\program files (x86)\\windows kits\\10\\include\\10.0.22621.0\\shared\\poppack.h",
            "c:\\program files (x86)\\windows kits\\10\\include\\10.0.22621.0\\shared\\pshpack4.h",
            "c:\\program files (x86)\\windows kits\\10\\include\\10.0.22621.0\\shared\\poppack.h",
            "c:\\program files (x86)\\windows kits\\10\\include\\10.0.22621.0\\um\\winuser.h",
            "c:\\program files (x86)\\windows kits\\10\\include\\10.0.22621.0\\shared\\pshpack2.h",
            "c:\\program files (x86)\\windows kits\\10\\include\\10.0.22621.0\\shared\\poppack.h",
            "c:\\program files (x86)\\windows kits\\10\\include\\10.0.22621.0\\shared\\tvout.h",
            "c:\\program files (x86)\\windows kits\\10\\include\\10.0.22621.0\\um\\winnls.h",
            "c:\\program files (x86)\\windows kits\\10\\include\\10.0.22621.0\\um\\datetimeapi.h",
            "c:\\program files (x86)\\windows kits\\10\\include\\10.0.22621.0\\um\\stringapiset.h",
            "c:\\program files (x86)\\windows kits\\10\\include\\10.0.22621.0\\um\\winnls.h",
            "c:\\program files (x86)\\windows kits\\10\\include\\10.0.22621.0\\um\\wincon.h",
            "c:\\program files (x86)\\windows kits\\10\\include\\10.0.22621.0\\um\\wincontypes.h",
            "c:\\program files (x86)\\windows kits\\10\\include\\10.0.22621.0\\um\\consoleapi.h",
            "c:\\program files (x86)\\windows kits\\10\\include\\10.0.22621.0\\um\\consoleapi2.h",
            "c:\\program files (x86)\\windows kits\\10\\include\\10.0.22621.0\\um\\consoleapi3.h",
            "c:\\program files (x86)\\windows kits\\10\\include\\10.0.22621.0\\um\\winver.h",
            "c:\\program files (x86)\\windows kits\\10\\include\\10.0.22621.0\\um\\verrsrc.h",
            "c:\\program files (x86)\\windows kits\\10\\include\\10.0.22621.0\\um\\winreg.h",
            "c:\\program files (x86)\\windows kits\\10\\include\\10.0.22621.0\\um\\reason.h",
            "c:\\program files (x86)\\windows kits\\10\\include\\10.0.22621.0\\um\\winnetwk.h",
            "c:\\program files (x86)\\windows kits\\10\\include\\10.0.22621.0\\shared\\wnnc.h",
            "c:\\program files (x86)\\windows kits\\10\\include\\10.0.22621.0\\shared\\stralign.h",
            "c:\\program files (x86)\\windows kits\\10\\include\\10.0.22621.0\\um\\imm.h",
            "c:\\program files (x86)\\windows kits\\10\\include\\10.0.22621.0\\um\\ime_cmodes.h",
            "d:\\ue_5.1\\engine\\source\\runtime\\core\\public\\windows\\postwindowsapi.h",
            "d:\\ue_5.1\\engine\\source\\runtime\\core\\public\\windows\\allowwindowsplatformatomics.h",
            "d:\\palworldsdk\\plugins\\wwise\\thirdparty\\include\\ak\\soundengine\\common\\aksoundengine.h",
            "d:\\palworldsdk\\plugins\\wwise\\thirdparty\\include\\ak\\soundengine\\common\\aksoundengineexport.h",
            "d:\\palworldsdk\\plugins\\wwise\\thirdparty\\include\\ak\\akplatforms.h",
            "d:\\palworldsdk\\plugins\\wwise\\thirdparty\\include\\ak\\soundengine\\platforms\\windows\\aktypes.h",
            "d:\\palworldsdk\\plugins\\wwise\\thirdparty\\include\\ak\\soundengine\\common\\aktypes.h",
            "d:\\palworldsdk\\plugins\\wwise\\thirdparty\\include\\ak\\soundengine\\common\\iakplugin.h",
            "d:\\palworldsdk\\plugins\\wwise\\thirdparty\\include\\ak\\soundengine\\common\\akcommondefs.h",
            "d:\\palworldsdk\\plugins\\wwise\\thirdparty\\include\\ak\\soundengine\\common\\akspeakerconfig.h",
            "d:\\palworldsdk\\plugins\\wwise\\thirdparty\\include\\ak\\soundengine\\common\\akspeakervolumes.h",
            "d:\\palworldsdk\\plugins\\wwise\\thirdparty\\include\\ak\\soundengine\\platforms\\generic\\akspeakervolumes.h",
            "d:\\palworldsdk\\plugins\\wwise\\thirdparty\\include\\ak\\tools\\common\\akplatformfuncs.h",
            "d:\\palworldsdk\\plugins\\wwise\\thirdparty\\include\\ak\\soundengine\\common\\akatomic.h",
            "d:\\palworldsdk\\plugins\\wwise\\thirdparty\\include\\ak\\soundengine\\platforms\\windows\\akatomic.h",
            "d:\\palworldsdk\\plugins\\wwise\\thirdparty\\include\\ak\\tools\\win32\\akplatformfuncs.h",
            "d:\\palworldsdk\\plugins\\wwise\\thirdparty\\include\\ak\\tools\\common\\akassert.h",
            "c:\\program files (x86)\\windows kits\\10\\include\\10.0.22621.0\\ucrt\\math.h",
            "d:\\palworldsdk\\plugins\\wwise\\thirdparty\\include\\ak\\soundengine\\common\\iakpluginmemalloc.h",
            "d:\\palworldsdk\\plugins\\wwise\\thirdparty\\include\\ak\\soundengine\\common\\akmemorymgr.h",
            "d:\\palworldsdk\\plugins\\wwise\\thirdparty\\include\\ak\\tools\\common\\akarray.h",
            "d:\\palworldsdk\\plugins\\wwise\\thirdparty\\include\\ak\\tools\\common\\akobject.h",
            "d:\\palworldsdk\\plugins\\wwise\\thirdparty\\include\\ak\\tools\\common\\akstring.h",
            "d:\\palworldsdk\\plugins\\wwise\\thirdparty\\include\\ak\\tools\\common\\akfnvhash.h",
            "d:\\palworldsdk\\plugins\\wwise\\thirdparty\\include\\ak\\tools\\common\\akhashlist.h",
            "d:\\palworldsdk\\plugins\\wwise\\thirdparty\\include\\ak\\tools\\common\\akkeydef.h",
            "d:\\palworldsdk\\plugins\\wwise\\thirdparty\\include\\ak\\soundengine\\common\\iakrtpcsubscriber.h",
            "d:\\palworldsdk\\plugins\\wwise\\thirdparty\\include\\ak\\soundengine\\common\\akfputilities.h",
            "d:\\palworldsdk\\plugins\\wwise\\thirdparty\\include\\ak\\tools\\common\\aklock.h",
            "d:\\palworldsdk\\plugins\\wwise\\thirdparty\\include\\ak\\tools\\win32\\aklock.h",
            "d:\\palworldsdk\\plugins\\wwise\\thirdparty\\include\\ak\\tools\\common\\akmonitorerror.h",
            "d:\\palworldsdk\\plugins\\wwise\\thirdparty\\include\\ak\\soundengine\\common\\iakprocessorfeatures.h",
            "d:\\palworldsdk\\plugins\\wwise\\thirdparty\\include\\ak\\soundengine\\common\\iakplatformcontext.h",
            "d:\\palworldsdk\\plugins\\wwise\\thirdparty\\include\\ak\\soundengine\\common\\akmiditypes.h",
            "d:\\palworldsdk\\plugins\\wwise\\thirdparty\\include\\ak\\soundengine\\common\\akcallback.h",
            "c:\\program files (x86)\\windows kits\\10\\include\\10.0.22621.0\\ucrt\\math.h",
            "d:\\palworldsdk\\plugins\\wwise\\thirdparty\\include\\ak\\soundengine\\platforms\\windows\\akwinsoundengine.h",
            "d:\\palworldsdk\\plugins\\wwise\\thirdparty\\include\\ak\\soundengine\\platforms\\windows\\akplatformcontext.h",
            "d:\\palworldsdk\\plugins\\wwise\\thirdparty\\include\\ak\\spatialaudio\\common\\akspatialaudio.h",
            "d:\\palworldsdk\\plugins\\wwise\\thirdparty\\include\\ak\\spatialaudio\\common\\akspatialaudiotypes.h",
            "d:\\palworldsdk\\plugins\\wwise\\thirdparty\\include\\ak\\tools\\common\\akkeyarray.h",
            "d:\\palworldsdk\\plugins\\wwise\\thirdparty\\include\\ak\\tools\\common\\akset.h",
            "d:\\palworldsdk\\plugins\\wwise\\thirdparty\\include\\ak\\plugin\\akreflectgamedata.h",
            "d:\\palworldsdk\\plugins\\wwise\\thirdparty\\include\\ak\\ibytes.h",
            "d:\\palworldsdk\\plugins\\wwise\\thirdparty\\include\\ak\\soundengine\\common\\akmodule.h",
            "d:\\palworldsdk\\plugins\\wwise\\thirdparty\\include\\ak\\soundengine\\common\\iakstreammgr.h",
            "d:\\palworldsdk\\plugins\\wwise\\thirdparty\\include\\ak\\soundengine\\common\\akstreammgrmodule.h",
            "d:\\palworldsdk\\plugins\\wwise\\thirdparty\\include\\ak\\musicengine\\common\\akmusicengine.h",
            "d:\\palworldsdk\\plugins\\wwise\\thirdparty\\include\\ak\\comm\\akcommunication.h",
            "d:\\palworldsdk\\plugins\\wwise\\thirdparty\\include\\ak\\soundengine\\common\\akqueryparameters.h",
            "d:\\ue_5.1\\engine\\source\\runtime\\core\\public\\windows\\hidewindowsplatformtypes.h",
            "d:\\ue_5.1\\engine\\source\\runtime\\core\\public\\windows\\hidewindowsplatformatomics.h",
            "d:\\palworldsdk\\plugins\\wwise\\source\\akaudio\\classes\\akbankmanager.h",
            "d:\\palworldsdk\\plugins\\wwise\\source\\akaudio\\classes\\akgameplaytypes.h",
            "d:\\palworldsdk\\plugins\\wwise\\source\\akaudio\\classes\\platforms\\akueplatform.h",
            "d:\\palworldsdk\\plugins\\wwise\\source\\akaudio\\classes\\platforms\\akplatform_windows\\akwindowsplatform.h",
            "d:\\palworldsdk\\plugins\\wwise\\source\\akaudio\\classes\\platforms\\akplatformbase.h",
            "d:\\palworldsdk\\plugins\\wwise\\source\\akaudio\\classes\\platforms\\akplatform_windows\\akwindowsinitializationsettings.h",
            "d:\\palworldsdk\\plugins\\wwise\\source\\akaudio\\classes\\initializationsettings\\akinitializationsettings.h",
            "d:\\palworldsdk\\plugins\\wwise\\intermediate\\build\\win64\\unrealeditor\\inc\\akaudio\\uht\\akinitializationsettings.generated.h",
            "d:\\palworldsdk\\plugins\\wwise\\source\\akaudio\\classes\\initializationsettings\\akplatforminitialisationsettingsbase.h",
            "d:\\palworldsdk\\plugins\\wwise\\intermediate\\build\\win64\\unrealeditor\\inc\\akaudio\\uht\\akplatforminitialisationsettingsbase.generated.h",
            "d:\\palworldsdk\\plugins\\wwise\\intermediate\\build\\win64\\unrealeditor\\inc\\akaudio\\uht\\akwindowsinitializationsettings.generated.h",
            "d:\\palworldsdk\\plugins\\wwise\\intermediate\\build\\win64\\unrealeditor\\inc\\akaudio\\uht\\akgameplaytypes.generated.h",
            "d:\\ue_5.1\\engine\\source\\runtime\\engine\\classes\\engine\\streamablemanager.h",
            "d:\\palworldsdk\\plugins\\wwise\\source\\akaudio\\classes\\akenvironmentindex.h",
            "d:\\ue_5.1\\engine\\source\\runtime\\core\\public\\math\\genericoctree.h",
            "d:\\ue_5.1\\engine\\source\\runtime\\core\\public\\math\\genericoctreepublic.h",
            "d:\\ue_5.1\\engine\\source\\runtime\\core\\public\\math\\genericoctree.inl",
            "d:\\palworldsdk\\plugins\\wwise\\source\\akaudio\\classes\\akgroupvalue.h",
            "d:\\palworldsdk\\plugins\\wwise\\source\\akaudio\\classes\\akaudiotype.h",
            "d:\\palworldsdk\\plugins\\wwise\\intermediate\\build\\win64\\unrealeditor\\inc\\akaudio\\uht\\akaudiotype.generated.h",
            "d:\\palworldsdk\\plugins\\wwise\\intermediate\\build\\win64\\unrealeditor\\inc\\akaudio\\uht\\akgroupvalue.generated.h",
            "d:\\palworldsdk\\plugins\\wwise\\source\\akaudio\\classes\\akassetdata.h",
            "d:\\palworldsdk\\plugins\\wwise\\intermediate\\build\\win64\\unrealeditor\\inc\\akaudio\\uht\\akassetdata.generated.h",
            "d:\\palworldsdk\\plugins\\wwise\\source\\akaudio\\classes\\akunrealhelper.h",
            "d:\\palworldsdk\\plugins\\wwise\\source\\akaudio\\private\\akunrealiohook.h",
            "d:\\palworldsdk\\plugins\\wwise\\source\\akaudio\\private\\iakunrealiohook.h",
            "d:\\palworldsdk\\plugins\\wwise\\source\\akaudio\\private\\akmediamemorymanager.h",
            "d:\\palworldsdk\\plugins\\wwise\\source\\akaudio\\classes\\platforms\\akplatforminfo.h",
            "d:\\ue_5.1\\engine\\source\\runtime\\engine\\classes\\engine\\gameengine.h",
            "d:\\ue_5.1\\engine\\source\\runtime\\slate\\public\\widgets\\sviewport.h",
            "d:\\ue_5.1\\engine\\source\\runtime\\moviescenecapture\\public\\moviescenecapturehandle.h",
            "d:\\ue_5.1\\engine\\intermediate\\build\\win64\\unrealeditor\\inc\\engine\\uht\\gameengine.generated.h",
            "d:\\palworldsdk\\plugins\\wwise\\intermediate\\build\\win64\\unrealeditor\\inc\\akaudio\\uht\\akplatforminfo.generated.h",
            "d:\\ue_5.1\\engine\\source\\runtime\\core\\public\\async\\async.h",
            "d:\\palworldsdk\\plugins\\wwise\\source\\akaudio\\private\\akmediamemorymanager.cpp",
            "d:\\palworldsdk\\plugins\\wwise\\source\\akaudio\\private\\akreverbdescriptor.cpp",
            "d:\\palworldsdk\\plugins\\wwise\\source\\akaudio\\classes\\akreverbdescriptor.h",
            "d:\\palworldsdk\\plugins\\wwise\\intermediate\\build\\win64\\unrealeditor\\inc\\akaudio\\uht\\akreverbdescriptor.generated.h",
            "d:\\palworldsdk\\plugins\\wwise\\thirdparty\\include\\ak\\spatialaudio\\common\\akreverbestimation.h",
            "d:\\palworldsdk\\plugins\\wwise\\thirdparty\\include\\ak\\soundengine\\common\\akvirtualacoustics.h",
            "d:\\palworldsdk\\plugins\\wwise\\source\\akaudio\\classes\\akacoustictexturesetcomponent.h",
            "d:\\palworldsdk\\plugins\\wwise\\source\\akaudio\\classes\\aksettings.h",
            "d:\\palworldsdk\\plugins\\wwise\\source\\akaudio\\classes\\akacoustictexture.h",
            "d:\\palworldsdk\\plugins\\wwise\\intermediate\\build\\win64\\unrealeditor\\inc\\akaudio\\uht\\akacoustictexture.generated.h",
            "d:\\ue_5.1\\engine\\source\\runtime\\assetregistry\\public\\assetregistry\\assetregistrymodule.h",
            "d:\\ue_5.1\\engine\\source\\runtime\\assetregistry\\public\\assetregistry\\iassetregistry.h",
            "d:\\ue_5.1\\engine\\source\\runtime\\coreuobject\\public\\misc\\assetregistryinterface.h",
            "d:\\ue_5.1\\engine\\intermediate\\build\\win64\\unrealeditor\\inc\\assetregistry\\uht\\iassetregistry.generated.h",
            "d:\\palworldsdk\\plugins\\wwise\\source\\akaudio\\classes\\akrtpc.h",
            "d:\\palworldsdk\\plugins\\wwise\\intermediate\\build\\win64\\unrealeditor\\inc\\akaudio\\uht\\akrtpc.generated.h",
            "d:\\palworldsdk\\plugins\\wwise\\intermediate\\build\\win64\\unrealeditor\\inc\\akaudio\\uht\\aksettings.generated.h",
            "d:\\palworldsdk\\plugins\\wwise\\intermediate\\build\\win64\\unrealeditor\\inc\\akaudio\\uht\\akacoustictexturesetcomponent.generated.h",
            "d:\\palworldsdk\\plugins\\wwise\\source\\akaudio\\classes\\aklatereverbcomponent.h",
            "d:\\ue_5.1\\engine\\source\\runtime\\engine\\classes\\components\\textrendercomponent.h",
            "d:\\ue_5.1\\engine\\intermediate\\build\\win64\\unrealeditor\\inc\\engine\\uht\\textrendercomponent.generated.h",
            "d:\\palworldsdk\\plugins\\wwise\\intermediate\\build\\win64\\unrealeditor\\inc\\akaudio\\uht\\aklatereverbcomponent.generated.h",
            "d:\\palworldsdk\\plugins\\wwise\\source\\akaudio\\classes\\akroomcomponent.h",
            "d:\\ue_5.1\\engine\\source\\runtime\\engine\\classes\\gameframework\\volume.h",
            "d:\\ue_5.1\\engine\\intermediate\\build\\win64\\unrealeditor\\inc\\engine\\uht\\volume.generated.h",
            "d:\\palworldsdk\\plugins\\wwise\\source\\akaudio\\classes\\akgameobject.h",
            "d:\\palworldsdk\\plugins\\wwise\\intermediate\\build\\win64\\unrealeditor\\inc\\akaudio\\uht\\akgameobject.generated.h",
            "d:\\palworldsdk\\plugins\\wwise\\intermediate\\build\\win64\\unrealeditor\\inc\\akaudio\\uht\\akroomcomponent.generated.h",
            "d:\\palworldsdk\\plugins\\wwise\\source\\akaudio\\classes\\akcomponenthelpers.h",
            "d:\\ue_5.1\\engine\\source\\runtime\\engine\\classes\\components\\shapecomponent.h",
            "d:\\ue_5.1\\engine\\intermediate\\build\\win64\\unrealeditor\\inc\\engine\\uht\\shapecomponent.generated.h",
            "d:\\ue_5.1\\engine\\source\\runtime\\engine\\classes\\components\\brushcomponent.h",
            "d:\\ue_5.1\\engine\\intermediate\\build\\win64\\unrealeditor\\inc\\engine\\uht\\brushcomponent.generated.h",
            "d:\\palworldsdk\\plugins\\wwise\\source\\akaudio\\private\\akreverbvolume.cpp",
            "d:\\palworldsdk\\plugins\\wwise\\source\\akaudio\\classes\\akreverbvolume.h",
            "d:\\palworldsdk\\plugins\\wwise\\intermediate\\build\\win64\\unrealeditor\\inc\\akaudio\\uht\\akreverbvolume.generated.h",
            "d:\\palworldsdk\\plugins\\wwise\\source\\akaudio\\private\\akcustomversion.h",
            "d:\\palworldsdk\\plugins\\wwise\\source\\akaudio\\private\\akroomcomponent.cpp",
            "d:\\palworldsdk\\plugins\\wwise\\source\\akaudio\\classes\\akacousticportal.h",
            "d:\\palworldsdk\\plugins\\wwise\\source\\akaudio\\classes\\occlusionobstructionservice\\akportalocclusionobstructionservice.h",
            "d:\\palworldsdk\\plugins\\wwise\\source\\akaudio\\classes\\occlusionobstructionservice\\akocclusionobstructionservice.h",
            "d:\\palworldsdk\\plugins\\wwise\\intermediate\\build\\win64\\unrealeditor\\inc\\akaudio\\uht\\akacousticportal.generated.h",
            "d:\\palworldsdk\\plugins\\wwise\\source\\akaudio\\classes\\akgeometrycomponent.h",
            "d:\\palworldsdk\\plugins\\wwise\\source\\akaudio\\classes\\akgeometrydata.h",
            "d:\\palworldsdk\\plugins\\wwise\\intermediate\\build\\win64\\unrealeditor\\inc\\akaudio\\uht\\akgeometrydata.generated.h",
            "d:\\palworldsdk\\plugins\\wwise\\intermediate\\build\\win64\\unrealeditor\\inc\\akaudio\\uht\\akgeometrycomponent.generated.h",
            "d:\\palworldsdk\\plugins\\wwise\\source\\akaudio\\classes\\aksurfacereflectorsetcomponent.h",
            "d:\\palworldsdk\\plugins\\wwise\\source\\akaudio\\classes\\aksurfacereflectorsetutils.h",
            "d:\\palworldsdk\\plugins\\wwise\\intermediate\\build\\win64\\unrealeditor\\inc\\akaudio\\uht\\aksurfacereflectorsetutils.generated.h",
            "d:\\palworldsdk\\plugins\\wwise\\intermediate\\build\\win64\\unrealeditor\\inc\\akaudio\\uht\\aksurfacereflectorsetcomponent.generated.h",
            "d:\\ue_5.1\\engine\\source\\runtime\\engine\\public\\engineutils.h",
            "d:\\ue_5.1\\engine\\source\\runtime\\engine\\classes\\gameframework\\worldsettings.h",
            "d:\\ue_5.1\\engine\\source\\runtime\\engine\\classes\\gameframework\\damagetype.h",
            "d:\\ue_5.1\\engine\\intermediate\\build\\win64\\unrealeditor\\inc\\engine\\uht\\damagetype.generated.h",
            "d:\\ue_5.1\\engine\\source\\runtime\\engine\\classes\\gameframework\\info.h",
            "d:\\ue_5.1\\engine\\intermediate\\build\\win64\\unrealeditor\\inc\\engine\\uht\\info.generated.h",
            "d:\\ue_5.1\\engine\\source\\runtime\\engine\\classes\\sound\\audiovolume.h",
            "d:\\ue_5.1\\engine\\source\\runtime\\engine\\classes\\sound\\reverbsettings.h",
            "d:\\ue_5.1\\engine\\intermediate\\build\\win64\\unrealeditor\\inc\\engine\\uht\\reverbsettings.generated.h",
            "d:\\ue_5.1\\engine\\intermediate\\build\\win64\\unrealeditor\\inc\\engine\\uht\\audiovolume.generated.h",
            "d:\\ue_5.1\\engine\\source\\runtime\\coreuobject\\public\\uobject\\constructorhelpers.h",
            "d:\\ue_5.1\\engine\\source\\runtime\\engine\\public\\worldpartition\\worldpartitioneditorperprojectusersettings.h",
            "d:\\ue_5.1\\engine\\intermediate\\build\\win64\\unrealeditor\\inc\\engine\\uht\\worldpartitioneditorperprojectusersettings.generated.h",
            "d:\\ue_5.1\\engine\\intermediate\\build\\win64\\unrealeditor\\inc\\engine\\uht\\worldsettings.generated.h",
            "d:\\palworldsdk\\plugins\\wwise\\source\\akaudio\\classes\\akaudioevent.h",
            "d:\\palworldsdk\\plugins\\wwise\\source\\akaudio\\classes\\akassetbase.h",
            "d:\\palworldsdk\\plugins\\wwise\\intermediate\\build\\win64\\unrealeditor\\inc\\akaudio\\uht\\akassetbase.generated.h",
            "d:\\palworldsdk\\plugins\\wwise\\intermediate\\build\\win64\\unrealeditor\\inc\\akaudio\\uht\\akaudioevent.generated.h",
            "d:\\palworldsdk\\plugins\\wwise\\source\\akaudio\\classes\\akdrawroomcomponent.h",
            "d:\\palworldsdk\\plugins\\wwise\\intermediate\\build\\win64\\unrealeditor\\inc\\akaudio\\uht\\akdrawroomcomponent.generated.h",
            "d:\\palworldsdk\\plugins\\wwise\\source\\akaudio\\classes\\akspatialaudiohelper.h",
            "d:\\palworldsdk\\plugins\\wwise\\source\\akaudio\\private\\akrtpc.cpp",
            "d:\\palworldsdk\\plugins\\wwise\\source\\akaudio\\private\\aksettings.cpp",
            "d:\\palworldsdk\\plugins\\wwise\\source\\akaudio\\classes\\akauxbus.h",
            "d:\\palworldsdk\\plugins\\wwise\\intermediate\\build\\win64\\unrealeditor\\inc\\akaudio\\uht\\akauxbus.generated.h",
            "d:\\palworldsdk\\plugins\\wwise\\source\\akaudio\\classes\\aksettingsperuser.h",
            "d:\\palworldsdk\\plugins\\wwise\\source\\akaudio\\public\\akwaapiclient.h",
            "d:\\ue_5.1\\engine\\source\\runtime\\json\\public\\serialization\\jsonwriter.h",
            "d:\\ue_5.1\\engine\\source\\runtime\\json\\public\\serialization\\jsontypes.h",
            "d:\\ue_5.1\\engine\\source\\runtime\\json\\public\\serialization\\jsonserializer.h",
            "d:\\ue_5.1\\engine\\source\\runtime\\json\\public\\dom\\jsonvalue.h",
            "d:\\ue_5.1\\engine\\source\\runtime\\json\\public\\dom\\jsonobject.h",
            "d:\\ue_5.1\\engine\\source\\runtime\\json\\public\\jsonglobals.h",
            "d:\\ue_5.1\\engine\\source\\runtime\\json\\public\\serialization\\jsonreader.h",
            "d:\\palworldsdk\\plugins\\wwise\\thirdparty\\include\\ak\\wwiseauthoringapi\\waapi.h",
            "d:\\palworldsdk\\plugins\\wwise\\intermediate\\build\\win64\\unrealeditor\\inc\\akaudio\\uht\\aksettingsperuser.generated.h",
            "d:\\palworldsdk\\plugins\\wwise\\source\\akaudio\\private\\stringmatchalgos\\array2d.h",
            "d:\\palworldsdk\\plugins\\wwise\\source\\akaudio\\private\\stringmatchalgos\\stringmatching.h",
            "d:\\palworldsdk\\plugins\\wwise\\source\\akaudio\\classes\\akaudiostyle.h",
            "d:\\palworldsdk\\plugins\\wwise\\source\\akaudio\\classes\\waapipicker\\wwisetreeitem.h",
            "d:\\palworldsdk\\plugins\\wwise\\source\\akaudio\\classes\\wwiseitemtype.h",
            "d:\\palworldsdk\\plugins\\wwise\\intermediate\\build\\win64\\unrealeditor\\inc\\akaudio\\uht\\wwiseitemtype.generated.h",
            "d:\\ue_5.1\\engine\\source\\developer\\assettools\\public\\assettoolsmodule.h",
            "d:\\ue_5.1\\engine\\source\\developer\\assettools\\public\\iassettools.h",
            "d:\\ue_5.1\\engine\\source\\developer\\assettools\\public\\assettypecategories.h",
            "d:\\ue_5.1\\engine\\source\\developer\\assettools\\public\\iassettypeactions.h",
            "d:\\ue_5.1\\engine\\source\\developer\\merge\\public\\merge.h",
            "d:\\ue_5.1\\engine\\source\\editor\\unrealed\\classes\\thumbnailrendering\\thumbnailmanager.h",
            "d:\\ue_5.1\\engine\\source\\editor\\unrealed\\classes\\thumbnailrendering\\thumbnailrenderer.h",
            "d:\\ue_5.1\\engine\\intermediate\\build\\win64\\unrealeditor\\inc\\unrealed\\uht\\thumbnailrenderer.generated.h",
            "d:\\ue_5.1\\engine\\intermediate\\build\\win64\\unrealeditor\\inc\\unrealed\\uht\\thumbnailmanager.generated.h",
            "d:\\ue_5.1\\engine\\intermediate\\build\\win64\\unrealeditor\\inc\\assettools\\uht\\iassettypeactions.generated.h",
            "d:\\ue_5.1\\engine\\source\\editor\\unrealed\\public\\automatedassetimportdata.h",
            "d:\\ue_5.1\\engine\\intermediate\\build\\win64\\unrealeditor\\inc\\unrealed\\uht\\automatedassetimportdata.generated.h",
            "d:\\ue_5.1\\engine\\intermediate\\build\\win64\\unrealeditor\\inc\\assettools\\uht\\iassettools.generated.h",
            "d:\\ue_5.1\\engine\\source\\runtime\\core\\public\\misc\\filehelper.h",
            "d:\\ue_5.1\\engine\\source\\developer\\developertoolsettings\\classes\\settings\\projectpackagingsettings.h",
            "d:\\ue_5.1\\engine\\intermediate\\build\\win64\\unrealeditor\\inc\\developertoolsettings\\uht\\projectpackagingsettings.generated.h",
            "d:\\ue_5.1\\engine\\source\\developer\\settingseditor\\public\\isettingseditormodule.h",
            "d:\\ue_5.1\\engine\\source\\editor\\unrealed\\public\\objecttools.h",
            "d:\\ue_5.1\\engine\\source\\developer\\collectionmanager\\public\\collectionmanagertypes.h",
            "d:\\ue_5.1\\engine\\source\\developer\\sourcecontrol\\public\\isourcecontrolstate.h",
            "d:\\palworldsdk\\plugins\\wwise\\source\\akaudio\\classes\\akwaapiutils.h",
            "d:\\palworldsdk\\plugins\\wwise\\source\\akaudio\\private\\aksettingsperuser.cpp",
            "d:\\palworldsdk\\plugins\\wwise\\source\\akaudio\\private\\akspatialaudiodrawutils.cpp",
            "d:\\palworldsdk\\plugins\\wwise\\source\\akaudio\\classes\\akspatialaudiodrawutils.h",
            "d:\\palworldsdk\\plugins\\wwise\\source\\akaudio\\classes\\akspatialaudiovolume.h",
            "d:\\palworldsdk\\plugins\\wwise\\intermediate\\build\\win64\\unrealeditor\\inc\\akaudio\\uht\\akspatialaudiovolume.generated.h",
            "d:\\ue_5.1\\engine\\source\\editor\\unrealed\\classes\\settings\\editorstylesettings.h",
            "d:\\ue_5.1\\engine\\intermediate\\build\\win64\\unrealeditor\\inc\\unrealed\\uht\\editorstylesettings.generated.h",
            "d:\\palworldsdk\\plugins\\wwise\\source\\akaudio\\private\\akspatialaudiohelper.cpp",
            "d:\\palworldsdk\\plugins\\wwise\\source\\akaudio\\private\\akspatialaudiovolume.cpp",
            "d:\\ue_5.1\\engine\\source\\runtime\\engine\\classes\\engine\\brushbuilder.h",
            "d:\\ue_5.1\\engine\\intermediate\\build\\win64\\unrealeditor\\inc\\engine\\uht\\brushbuilder.generated.h",
            "d:\\ue_5.1\\engine\\source\\runtime\\coreuobject\\public\\misc\\transactionobjectevent.h",
            "d:\\palworldsdk\\plugins\\wwise\\source\\akaudio\\classes\\gte\\mathematics\\math.h",
            "c:\\program files\\microsoft visual studio\\2022\\community\\vc\\tools\\msvc\\14.33.31629\\include\\cfenv",
            "d:\\palworldsdk\\plugins\\wwise\\source\\akaudio\\classes\\gte\\mathematics\\uintegerap32.h",
            "d:\\palworldsdk\\plugins\\wwise\\source\\akaudio\\classes\\gte\\mathematics\\logger.h",
            "c:\\program files\\microsoft visual studio\\2022\\community\\vc\\tools\\msvc\\14.33.31629\\include\\mutex",
            "c:\\program files\\microsoft visual studio\\2022\\community\\vc\\tools\\msvc\\14.33.31629\\include\\__msvc_chrono.hpp",
            "c:\\program files\\microsoft visual studio\\2022\\community\\vc\\tools\\msvc\\14.33.31629\\include\\ratio",
            "c:\\program files\\microsoft visual studio\\2022\\community\\vc\\tools\\msvc\\14.33.31629\\include\\thread",
            "c:\\program files (x86)\\windows kits\\10\\include\\10.0.22621.0\\ucrt\\process.h",
            "c:\\program files (x86)\\windows kits\\10\\include\\10.0.22621.0\\ucrt\\corecrt_startup.h",
            "c:\\program files (x86)\\windows kits\\10\\include\\10.0.22621.0\\ucrt\\math.h",
            "c:\\program files\\microsoft visual studio\\2022\\community\\vc\\tools\\msvc\\14.33.31629\\include\\vcruntime_startup.h",
            "c:\\program files\\microsoft visual studio\\2022\\community\\vc\\tools\\msvc\\14.33.31629\\include\\set",
            "c:\\program files\\microsoft visual studio\\2022\\community\\vc\\tools\\msvc\\14.33.31629\\include\\xtree",
            "c:\\program files\\microsoft visual studio\\2022\\community\\vc\\tools\\msvc\\14.33.31629\\include\\string",
            "d:\\palworldsdk\\plugins\\wwise\\source\\akaudio\\classes\\gte\\mathematics\\uintegeralu32.h",
            "d:\\palworldsdk\\plugins\\wwise\\source\\akaudio\\classes\\gte\\mathematics\\bithacks.h",
            "c:\\program files\\microsoft visual studio\\2022\\community\\vc\\tools\\msvc\\14.33.31629\\include\\array",
            "d:\\palworldsdk\\plugins\\wwise\\source\\akaudio\\classes\\gte\\mathematics\\bsrational.h",
            "d:\\palworldsdk\\plugins\\wwise\\source\\akaudio\\classes\\gte\\mathematics\\bsnumber.h",
            "d:\\palworldsdk\\plugins\\wwise\\source\\akaudio\\classes\\gte\\mathematics\\ieeebinary.h",
            "d:\\palworldsdk\\plugins\\wwise\\source\\akaudio\\classes\\gte\\mathematics\\minimumvolumebox3.h",
            "d:\\palworldsdk\\plugins\\wwise\\source\\akaudio\\classes\\gte\\mathematics\\convexhull3.h",
            "d:\\palworldsdk\\plugins\\wwise\\source\\akaudio\\classes\\gte\\mathematics\\etmanifoldmesh.h",
            "d:\\palworldsdk\\plugins\\wwise\\source\\akaudio\\classes\\gte\\mathematics\\edgekey.h",
            "d:\\palworldsdk\\plugins\\wwise\\source\\akaudio\\classes\\gte\\mathematics\\featurekey.h",
            "d:\\palworldsdk\\plugins\\wwise\\source\\akaudio\\classes\\gte\\mathematics\\trianglekey.h",
            "c:\\program files\\microsoft visual studio\\2022\\community\\vc\\tools\\msvc\\14.33.31629\\include\\map",
            "d:\\palworldsdk\\plugins\\wwise\\source\\akaudio\\classes\\gte\\mathematics\\primalquery3.h",
            "d:\\palworldsdk\\plugins\\wwise\\source\\akaudio\\classes\\gte\\mathematics\\vector3.h",
            "d:\\palworldsdk\\plugins\\wwise\\source\\akaudio\\classes\\gte\\mathematics\\vector.h",
            "d:\\palworldsdk\\plugins\\wwise\\source\\akaudio\\classes\\gte\\mathematics\\line.h",
            "d:\\palworldsdk\\plugins\\wwise\\source\\akaudio\\classes\\gte\\mathematics\\hyperplane.h",
            "d:\\palworldsdk\\plugins\\wwise\\source\\akaudio\\classes\\gte\\mathematics\\matrix.h",
            "d:\\palworldsdk\\plugins\\wwise\\source\\akaudio\\classes\\gte\\mathematics\\gaussianelimination.h",
            "d:\\palworldsdk\\plugins\\wwise\\source\\akaudio\\classes\\gte\\mathematics\\lexicoarray2.h",
            "d:\\palworldsdk\\plugins\\wwise\\source\\akaudio\\classes\\gte\\mathematics\\singularvaluedecomposition.h",
            "d:\\palworldsdk\\plugins\\wwise\\source\\akaudio\\classes\\gte\\mathematics\\rangeiteration.h",
            "d:\\palworldsdk\\plugins\\wwise\\source\\akaudio\\classes\\gte\\mathematics\\minimumareabox2.h",
            "d:\\palworldsdk\\plugins\\wwise\\source\\akaudio\\classes\\gte\\mathematics\\orientedbox.h",
            "d:\\palworldsdk\\plugins\\wwise\\source\\akaudio\\classes\\gte\\mathematics\\convexhull2.h",
            "d:\\palworldsdk\\plugins\\wwise\\source\\akaudio\\classes\\gte\\mathematics\\primalquery2.h",
            "d:\\palworldsdk\\plugins\\wwise\\source\\akaudio\\classes\\gte\\mathematics\\vector2.h",
            "d:\\palworldsdk\\plugins\\wwise\\source\\akaudio\\private\\akspotreflector.cpp",
            "d:\\palworldsdk\\plugins\\wwise\\source\\akaudio\\classes\\akspotreflector.h",
            "d:\\palworldsdk\\plugins\\wwise\\intermediate\\build\\win64\\unrealeditor\\inc\\akaudio\\uht\\akspotreflector.generated.h",
            "d:\\palworldsdk\\plugins\\wwise\\source\\akaudio\\classes\\akcomponent.h",
            "d:\\palworldsdk\\plugins\\wwise\\source\\akaudio\\classes\\occlusionobstructionservice\\akcomponentocclusionobstructionservice.h",
            "d:\\palworldsdk\\plugins\\wwise\\intermediate\\build\\win64\\unrealeditor\\inc\\akaudio\\uht\\akcomponent.generated.h",
            "d:\\ue_5.1\\engine\\source\\runtime\\engine\\classes\\components\\billboardcomponent.h",
            "d:\\ue_5.1\\engine\\intermediate\\build\\win64\\unrealeditor\\inc\\engine\\uht\\billboardcomponent.generated.h",
            "d:\\palworldsdk\\plugins\\wwise\\source\\akaudio\\private\\akstatevalue.cpp",
            "d:\\palworldsdk\\plugins\\wwise\\source\\akaudio\\classes\\akstatevalue.h",
            "d:\\palworldsdk\\plugins\\wwise\\intermediate\\build\\win64\\unrealeditor\\inc\\akaudio\\uht\\akstatevalue.generated.h",
            "d:\\palworldsdk\\plugins\\wwise\\source\\akaudio\\private\\aksubmixinputcomponent.cpp",
            "d:\\palworldsdk\\plugins\\wwise\\source\\akaudio\\classes\\aksubmixinputcomponent.h",
            "d:\\ue_5.1\\engine\\source\\runtime\\engine\\public\\audiodevice.h",
            "d:\\ue_5.1\\engine\\source\\runtime\\engine\\classes\\components\\audiocomponent.h",
            "d:\\ue_5.1\\engine\\source\\runtime\\engine\\public\\audio\\soundparametercontrollerinterface.h",
            "d:\\ue_5.1\\engine\\intermediate\\build\\win64\\unrealeditor\\inc\\engine\\uht\\soundparametercontrollerinterface.generated.h",
            "d:\\ue_5.1\\engine\\source\\runtime\\audioextensions\\public\\iaudioparametertransmitter.h",
            "d:\\ue_5.1\\engine\\source\\runtime\\audiomixer\\public\\quartz\\audiomixerclockhandle.h",
            "d:\\ue_5.1\\engine\\source\\runtime\\engine\\classes\\sound\\quartzsubscription.h",
            "d:\\ue_5.1\\engine\\source\\runtime\\audiomixer\\public\\quartz\\quartzsubsystem.h",
            "d:\\ue_5.1\\engine\\source\\runtime\\audiomixer\\public\\quartz\\audiomixerclockmanager.h",
            "d:\\ue_5.1\\engine\\source\\runtime\\audiomixer\\public\\quartz\\audiomixerclock.h",
            "d:\\ue_5.1\\engine\\source\\runtime\\audiomixer\\public\\quartz\\quartzmetronome.h",
            "d:\\ue_5.1\\engine\\intermediate\\build\\win64\\unrealeditor\\inc\\audiomixer\\uht\\quartzsubsystem.generated.h",
            "d:\\ue_5.1\\engine\\intermediate\\build\\win64\\unrealeditor\\inc\\audiomixer\\uht\\audiomixerclockhandle.generated.h",
            "d:\\ue_5.1\\engine\\source\\runtime\\audiomixer\\public\\quartz\\audiomixerquantizedcommands.h",
            "d:\\ue_5.1\\engine\\source\\runtime\\engine\\classes\\sound\\soundwave.h",
            "d:\\ue_5.1\\engine\\source\\runtime\\engine\\classes\\sound\\soundbase.h",
            "d:\\ue_5.1\\engine\\source\\runtime\\engine\\classes\\sound\\audiosettings.h",
            "d:\\ue_5.1\\engine\\intermediate\\build\\win64\\unrealeditor\\inc\\engine\\uht\\audiosettings.generated.h",
            "d:\\ue_5.1\\engine\\source\\runtime\\engine\\classes\\sound\\soundclass.h",
            "d:\\ue_5.1\\engine\\source\\runtime\\engine\\public\\audiodynamicparameter.h",
            "d:\\ue_5.1\\engine\\source\\runtime\\engine\\classes\\sound\\soundmodulationdestination.h",
            "d:\\ue_5.1\\engine\\intermediate\\build\\win64\\unrealeditor\\inc\\engine\\uht\\soundmodulationdestination.generated.h",
            "d:\\ue_5.1\\engine\\source\\runtime\\engine\\classes\\sound\\soundwaveloadingbehavior.h",
            "d:\\ue_5.1\\engine\\intermediate\\build\\win64\\unrealeditor\\inc\\engine\\uht\\soundclass.generated.h",
            "d:\\ue_5.1\\engine\\source\\runtime\\engine\\classes\\sound\\soundtimecodeoffset.h",
            "d:\\ue_5.1\\engine\\intermediate\\build\\win64\\unrealeditor\\inc\\engine\\uht\\soundtimecodeoffset.generated.h",
            "d:\\ue_5.1\\engine\\source\\runtime\\engine\\classes\\sound\\soundconcurrency.h",
            "d:\\ue_5.1\\engine\\intermediate\\build\\win64\\unrealeditor\\inc\\engine\\uht\\soundconcurrency.generated.h",
            "d:\\ue_5.1\\engine\\source\\runtime\\engine\\classes\\sound\\soundgenerator.h",
            "d:\\ue_5.1\\engine\\intermediate\\build\\win64\\unrealeditor\\inc\\engine\\uht\\soundbase.generated.h",
            "d:\\ue_5.1\\engine\\source\\runtime\\engine\\classes\\sound\\soundwavetimecodeinfo.h",
            "d:\\ue_5.1\\engine\\intermediate\\build\\win64\\unrealeditor\\inc\\engine\\uht\\soundwavetimecodeinfo.generated.h",
            "d:\\ue_5.1\\engine\\source\\runtime\\engine\\classes\\sound\\soundgroups.h",
            "d:\\ue_5.1\\engine\\intermediate\\build\\win64\\unrealeditor\\inc\\engine\\uht\\soundgroups.generated.h",
            "d:\\ue_5.1\\engine\\source\\runtime\\audioplatformconfiguration\\public\\audiocompressionsettings.h",
            "d:\\ue_5.1\\engine\\intermediate\\build\\win64\\unrealeditor\\inc\\audioplatformconfiguration\\uht\\audiocompressionsettings.generated.h",
            "d:\\ue_5.1\\engine\\source\\runtime\\engine\\public\\contentstreaming.h",
            "d:\\ue_5.1\\engine\\source\\runtime\\engine\\public\\canvastypes.h",
            "d:\\ue_5.1\\engine\\intermediate\\build\\win64\\unrealeditor\\inc\\engine\\uht\\canvastypes.generated.h",
            "d:\\ue_5.1\\engine\\source\\runtime\\audioextensions\\public\\iwaveformtransformation.h",
            "d:\\ue_5.1\\engine\\intermediate\\build\\win64\\unrealeditor\\inc\\audioextensions\\uht\\iwaveformtransformation.generated.h",
            "d:\\ue_5.1\\engine\\intermediate\\build\\win64\\unrealeditor\\inc\\engine\\uht\\soundwave.generated.h",
            "d:\\ue_5.1\\engine\\intermediate\\build\\win64\\unrealeditor\\inc\\engine\\uht\\audiocomponent.generated.h",
            "d:\\ue_5.1\\engine\\source\\runtime\\signalprocessing\\public\\dsp\\multithreadedpatching.h",
            "d:\\ue_5.1\\engine\\source\\runtime\\engine\\public\\isubmixbufferlistener.h",
            "d:\\ue_5.1\\engine\\source\\runtime\\engine\\classes\\sound\\soundsubmix.h",
            "d:\\ue_5.1\\engine\\source\\runtime\\audioextensions\\public\\iaudioendpoint.h",
            "d:\\ue_5.1\\engine\\intermediate\\build\\win64\\unrealeditor\\inc\\audioextensions\\uht\\iaudioendpoint.generated.h",
            "d:\\ue_5.1\\engine\\source\\runtime\\audioextensions\\public\\isoundfieldendpoint.h",
            "d:\\ue_5.1\\engine\\intermediate\\build\\win64\\unrealeditor\\inc\\audioextensions\\uht\\isoundfieldendpoint.generated.h",
            "d:\\ue_5.1\\engine\\source\\runtime\\engine\\classes\\sound\\samplebufferio.h",
            "d:\\ue_5.1\\engine\\source\\runtime\\signalprocessing\\public\\samplebuffer.h",
            "d:\\ue_5.1\\engine\\source\\runtime\\engine\\classes\\sound\\soundeffectsubmix.h",
            "d:\\ue_5.1\\engine\\intermediate\\build\\win64\\unrealeditor\\inc\\engine\\uht\\soundeffectsubmix.generated.h",
            "d:\\ue_5.1\\engine\\source\\runtime\\signalprocessing\\public\\dsp\\spectrumanalyzer.h",
            "d:\\ue_5.1\\engine\\source\\runtime\\signalprocessing\\public\\dsp\\audiofft.h",
            "d:\\ue_5.1\\engine\\source\\runtime\\signalprocessing\\public\\dsp\\fftalgorithm.h",
            "d:\\ue_5.1\\engine\\intermediate\\build\\win64\\unrealeditor\\inc\\engine\\uht\\soundsubmix.generated.h",
            "d:\\ue_5.1\\engine\\source\\runtime\\engine\\classes\\sound\\soundmix.h",
            "d:\\ue_5.1\\engine\\intermediate\\build\\win64\\unrealeditor\\inc\\engine\\uht\\soundmix.generated.h",
            "d:\\ue_5.1\\engine\\source\\runtime\\engine\\classes\\sound\\soundsourcebus.h",
            "d:\\ue_5.1\\engine\\source\\runtime\\engine\\classes\\sound\\soundwaveprocedural.h",
            "d:\\ue_5.1\\engine\\intermediate\\build\\win64\\unrealeditor\\inc\\engine\\uht\\soundwaveprocedural.generated.h",
            "d:\\ue_5.1\\engine\\source\\runtime\\engine\\classes\\sound\\audiobus.h",
            "d:\\ue_5.1\\engine\\intermediate\\build\\win64\\unrealeditor\\inc\\engine\\uht\\audiobus.generated.h",
            "d:\\ue_5.1\\engine\\intermediate\\build\\win64\\unrealeditor\\inc\\engine\\uht\\soundsourcebus.generated.h",
            "d:\\ue_5.1\\engine\\source\\runtime\\engine\\public\\subsystems\\audioenginesubsystem.h",
            "d:\\ue_5.1\\engine\\intermediate\\build\\win64\\unrealeditor\\inc\\engine\\uht\\audioenginesubsystem.generated.h",
            "d:\\ue_5.1\\engine\\source\\runtime\\engine\\public\\audiovirtualloop.h",
            "d:\\ue_5.1\\engine\\source\\runtime\\engine\\public\\activesound.h",
            "d:\\ue_5.1\\engine\\source\\runtime\\engine\\public\\audio\\audiodebug.h",
            "d:\\ue_5.1\\engine\\source\\runtime\\signalprocessing\\public\\dsp\\volumefader.h",
            "d:\\palworldsdk\\plugins\\wwise\\source\\akaudio\\classes\\akaudioinputcomponent.h",
            "d:\\palworldsdk\\plugins\\wwise\\source\\akaudio\\classes\\akaudioinputmanager.h",
            "d:\\palworldsdk\\plugins\\wwise\\intermediate\\build\\win64\\unrealeditor\\inc\\akaudio\\uht\\akaudioinputcomponent.generated.h",
            "d:\\palworldsdk\\plugins\\wwise\\intermediate\\build\\win64\\unrealeditor\\inc\\akaudio\\uht\\aksubmixinputcomponent.generated.h",
            "d:\\ue_5.1\\engine\\source\\runtime\\audiomixer\\public\\audiomixerdevice.h",
            "d:\\palworldsdk\\plugins\\wwise\\source\\akaudio\\private\\aksurfacereflectorsetcomponent.cpp",
            "d:\\ue_5.1\\engine\\source\\runtime\\engine\\public\\editorsupportdelegates.h",
            "d:\\ue_5.1\\engine\\source\\runtime\\engine\\classes\\engine\\polys.h",
            "d:\\ue_5.1\\engine\\intermediate\\build\\win64\\unrealeditor\\inc\\engine\\uht\\polys.generated.h",
            "d:\\ue_5.1\\engine\\source\\editor\\unrealed\\public\\cameracontroller.h",
            "d:\\ue_5.1\\engine\\source\\editor\\unrealed\\public\\editormodetools.h",
            "d:\\ue_5.1\\engine\\source\\editor\\unrealed\\public\\editormodemanager.h",
            "d:\\ue_5.1\\engine\\source\\runtime\\slate\\public\\widgets\\layout\\swidgetswitcher.h",
            "d:\\ue_5.1\\engine\\source\\editor\\unrealed\\public\\edmode.h",
            "d:\\ue_5.1\\engine\\source\\editor\\unrealed\\public\\editormoderegistry.h",
            "d:\\ue_5.1\\engine\\source\\editor\\unrealed\\public\\tools\\uedmode.h",
            "d:\\ue_5.1\\engine\\intermediate\\build\\win64\\unrealeditor\\inc\\unrealed\\uht\\uedmode.generated.h",
            "d:\\ue_5.1\\engine\\source\\editor\\unrealed\\public\\tools\\legacyedmodewidgethelpers.h",
            "d:\\ue_5.1\\engine\\source\\editor\\unrealed\\public\\tools\\legacyedmodeinterfaces.h",
            "d:\\ue_5.1\\engine\\intermediate\\build\\win64\\unrealeditor\\inc\\unrealed\\uht\\legacyedmodeinterfaces.generated.h",
            "d:\\ue_5.1\\engine\\intermediate\\build\\win64\\unrealeditor\\inc\\unrealed\\uht\\legacyedmodewidgethelpers.generated.h",
            "d:\\ue_5.1\\engine\\source\\runtime\\typedelementruntime\\public\\elements\\framework\\typedelementselectionset.h",
            "d:\\ue_5.1\\engine\\source\\runtime\\typedelementruntime\\public\\elements\\framework\\typedelementinterfacecustomization.h",
            "d:\\ue_5.1\\engine\\source\\runtime\\typedelementframework\\public\\elements\\framework\\typedelementlist.h",
            "d:\\ue_5.1\\engine\\source\\runtime\\typedelementframework\\public\\elements\\framework\\typedelementcounter.h",
            "d:\\ue_5.1\\engine\\intermediate\\build\\win64\\unrealeditor\\inc\\typedelementframework\\uht\\typedelementcounter.generated.h",
            "d:\\ue_5.1\\engine\\source\\runtime\\typedelementruntime\\public\\elements\\framework\\typedelementlistobjectutil.h",
            "d:\\ue_5.1\\engine\\source\\runtime\\typedelementruntime\\public\\elements\\interfaces\\typedelementselectioninterface.h",
            "d:\\ue_5.1\\engine\\source\\runtime\\typedelementframework\\public\\elements\\framework\\typedelementlistproxy.h",
            "d:\\ue_5.1\\engine\\intermediate\\build\\win64\\unrealeditor\\inc\\typedelementframework\\uht\\typedelementlistproxy.generated.h",
            "d:\\ue_5.1\\engine\\intermediate\\build\\win64\\unrealeditor\\inc\\typedelementruntime\\uht\\typedelementselectioninterface.generated.h",
            "d:\\ue_5.1\\engine\\intermediate\\build\\win64\\unrealeditor\\inc\\typedelementruntime\\uht\\typedelementselectionset.generated.h",
            "d:\\ue_5.1\\engine\\source\\editor\\editorframework\\public\\editormodes.h",
            "d:\\ue_5.1\\engine\\source\\runtime\\engine\\classes\\kismet\\kismetmathlibrary.h",
            "d:\\ue_5.1\\engine\\intermediate\\build\\win64\\unrealeditor\\inc\\engine\\uht\\kismetmathlibrary.generated.h",
            "d:\\ue_5.1\\engine\\source\\runtime\\engine\\classes\\kismet\\kismetmathlibrary.inl",
            "d:\\ue_5.1\\engine\\source\\editor\\unrealed\\public\\leveleditorviewport.h",
            "d:\\ue_5.1\\engine\\source\\runtime\\engine\\classes\\camera\\cameracomponent.h",
            "d:\\ue_5.1\\engine\\intermediate\\build\\win64\\unrealeditor\\inc\\engine\\uht\\cameracomponent.generated.h",
            "d:\\ue_5.1\\engine\\plugins\\editor\\geometrymode\\source\\geometrymode\\public\\editorgeometry.h",
            "d:\\ue_5.1\\engine\\plugins\\editor\\geometrymode\\source\\geometrymode\\public\\geometryedmode.h",
            "d:\\palworldsdk\\plugins\\wwise\\source\\akaudio\\private\\aksurfacereflectorsetutils.cpp",
            "d:\\palworldsdk\\plugins\\wwise\\source\\akaudio\\private\\akswitchvalue.cpp",
            "d:\\palworldsdk\\plugins\\wwise\\source\\akaudio\\classes\\akswitchvalue.h",
            "d:\\palworldsdk\\plugins\\wwise\\intermediate\\build\\win64\\unrealeditor\\inc\\akaudio\\uht\\akswitchvalue.generated.h",
            "d:\\palworldsdk\\plugins\\wwise\\source\\akaudio\\private\\aktrigger.cpp",
            "d:\\palworldsdk\\plugins\\wwise\\source\\akaudio\\classes\\aktrigger.h",
            "d:\\palworldsdk\\plugins\\wwise\\intermediate\\build\\win64\\unrealeditor\\inc\\akaudio\\uht\\aktrigger.generated.h",
            "d:\\palworldsdk\\plugins\\wwise\\source\\akaudio\\private\\akunrealhelper.cpp",
            "d:\\ue_5.1\\engine\\source\\runtime\\projects\\public\\interfaces\\ipluginmanager.h",
            "d:\\ue_5.1\\engine\\source\\runtime\\projects\\public\\plugindescriptor.h",
            "d:\\ue_5.1\\engine\\source\\runtime\\projects\\public\\custombuildsteps.h",
            "d:\\ue_5.1\\engine\\source\\runtime\\projects\\public\\localizationdescriptor.h",
            "d:\\ue_5.1\\engine\\source\\runtime\\projects\\public\\moduledescriptor.h",
            "d:\\ue_5.1\\engine\\source\\runtime\\projects\\public\\pluginreferencedescriptor.h",
            "d:\\ue_5.1\\engine\\source\\runtime\\projects\\public\\versescope.h",
            "d:\\ue_5.1\\engine\\source\\developer\\sharedsettingswidgets\\public\\ssettingseditorcheckoutnotice.h",
            "d:\\ue_5.1\\engine\\source\\developer\\sourcecontrol\\public\\isourcecontrolmodule.h",
            "d:\\ue_5.1\\engine\\source\\runtime\\slate\\public\\widgets\\input\\shyperlink.h",
            "d:\\ue_5.1\\engine\\source\\runtime\\slate\\public\\widgets\\accessibility\\slateaccessiblewidgets.h",
            "d:\\ue_5.1\\engine\\source\\runtime\\slate\\public\\widgets\\layout\\sexpandablearea.h",
            "d:\\palworldsdk\\plugins\\wwise\\source\\akaudio\\private\\akunrealiohook.cpp",
            "d:\\palworldsdk\\plugins\\wwise\\source\\akaudio\\private\\akwaapiblueprints\\akwaapicalls.cpp",
            "d:\\palworldsdk\\plugins\\wwise\\source\\akaudio\\classes\\akwaapiblueprints\\akwaapicalls.h",
            "d:\\palworldsdk\\plugins\\wwise\\source\\akaudio\\classes\\akwaapiblueprints\\akwaapiuri.h",
            "d:\\ue_5.1\\engine\\source\\runtime\\slate\\public\\widgets\\input\\ssearchbox.h",
            "d:\\ue_5.1\\engine\\source\\runtime\\core\\public\\misc\\textfilter.h",
            "d:\\ue_5.1\\engine\\source\\runtime\\core\\public\\misc\\textfilterexpressionevaluator.h",
            "d:\\ue_5.1\\engine\\source\\runtime\\core\\public\\misc\\expressionparser.h",
            "d:\\ue_5.1\\engine\\source\\runtime\\core\\public\\misc\\textfilterutils.h",
            "d:\\palworldsdk\\plugins\\wwise\\intermediate\\build\\win64\\unrealeditor\\inc\\akaudio\\uht\\akwaapiuri.generated.h",
            "d:\\palworldsdk\\plugins\\wwise\\source\\akaudio\\classes\\akwaapiblueprints\\akwaapijsonmanager.h",
            "d:\\palworldsdk\\plugins\\wwise\\source\\akaudio\\classes\\akwaapiblueprints\\akwaapifieldnames.h",
            "d:\\palworldsdk\\plugins\\wwise\\intermediate\\build\\win64\\unrealeditor\\inc\\akaudio\\uht\\akwaapifieldnames.generated.h",
            "d:\\palworldsdk\\plugins\\wwise\\intermediate\\build\\win64\\unrealeditor\\inc\\akaudio\\uht\\akwaapijsonmanager.generated.h",
            "d:\\palworldsdk\\plugins\\wwise\\intermediate\\build\\win64\\unrealeditor\\inc\\akaudio\\uht\\akwaapicalls.generated.h",
            "d:\\palworldsdk\\plugins\\wwise\\source\\akaudio\\classes\\akwaapiblueprints\\akwaapiuricustomization.h",
            "d:\\palworldsdk\\plugins\\wwise\\source\\akaudio\\classes\\akwaapiblueprints\\akwaapifieldnamescustomization.h",
            "d:\\palworldsdk\\plugins\\wwise\\source\\akaudio\\private\\akwaapiblueprints\\akwaapifieldnames.cpp",
            "d:\\ue_5.1\\engine\\source\\runtime\\core\\public\\misc\\scopedslowtask.h",
            "d:\\palworldsdk\\plugins\\wwise\\source\\akaudio\\private\\akwaapiblueprints\\akwaapifieldnamescustomization.cpp",
            "d:\\ue_5.1\\engine\\source\\editor\\propertyeditor\\public\\detailwidgetrow.h",
            "d:\\ue_5.1\\engine\\source\\editor\\propertyeditor\\public\\idetailpropertyrow.h",
            "d:\\ue_5.1\\engine\\source\\editor\\propertyeditor\\public\\detailcategorybuilder.h",
            "d:\\ue_5.1\\engine\\source\\editor\\propertyeditor\\public\\idetailcustomnodebuilder.h",
            "d:\\ue_5.1\\engine\\source\\editor\\propertyeditor\\public\\detailbuildertypes.h",
            "d:\\ue_5.1\\engine\\source\\runtime\\umg\\public\\components\\slatewrappertypes.h",
            "d:\\ue_5.1\\engine\\intermediate\\build\\win64\\unrealeditor\\inc\\umg\\uht\\slatewrappertypes.generated.h",
            "d:\\palworldsdk\\plugins\\wwise\\source\\akaudio\\private\\akwaapiblueprints\\akwaapijsonmanager.cpp",
            "d:\\palworldsdk\\plugins\\wwise\\source\\akaudio\\private\\akwaapiblueprints\\akwaapiuri.cpp",
            "d:\\palworldsdk\\plugins\\wwise\\source\\akaudio\\private\\akwaapiblueprints\\akwaapiurilist.inc",
            "d:\\palworldsdk\\plugins\\wwise\\source\\akaudio\\private\\akwaapiblueprints\\akwaapiuricustomization.cpp",
            "d:\\palworldsdk\\plugins\\wwise\\source\\akaudio\\private\\akwaapiclient.cpp",
            "d:\\palworldsdk\\plugins\\wwise\\thirdparty\\include\\ak\\wwiseauthoringapi\\akautobahn\\client.h",
            "d:\\palworldsdk\\plugins\\wwise\\thirdparty\\include\\ak\\wwiseauthoringapi\\akautobahn\\autobahn.h",
            "c:\\program files\\microsoft visual studio\\2022\\community\\vc\\tools\\msvc\\14.33.31629\\include\\condition_variable",
            "c:\\program files\\microsoft visual studio\\2022\\community\\vc\\tools\\msvc\\14.33.31629\\include\\future",
            "c:\\program files\\microsoft visual studio\\2022\\community\\vc\\tools\\msvc\\14.33.31629\\include\\ppltasks.h",
            "c:\\program files\\microsoft visual studio\\2022\\community\\vc\\tools\\msvc\\14.33.31629\\include\\pplwin.h",
            "c:\\program files\\microsoft visual studio\\2022\\community\\vc\\tools\\msvc\\14.33.31629\\include\\pplinterface.h",
            "c:\\program files\\microsoft visual studio\\2022\\community\\vc\\tools\\msvc\\14.33.31629\\include\\ppltaskscheduler.h",
            "c:\\program files\\microsoft visual studio\\2022\\community\\vc\\tools\\msvc\\14.33.31629\\include\\crtdefs.h",
            "c:\\program files\\microsoft visual studio\\2022\\community\\vc\\tools\\msvc\\14.33.31629\\include\\pplcancellation_token.h",
            "c:\\program files\\microsoft visual studio\\2022\\community\\vc\\tools\\msvc\\14.33.31629\\include\\queue",
            "c:\\program files\\microsoft visual studio\\2022\\community\\vc\\tools\\msvc\\14.33.31629\\include\\deque",
            "d:\\palworldsdk\\plugins\\wwise\\thirdparty\\include\\ak\\wwiseauthoringapi\\akautobahn\\akvariant.h",
            "d:\\palworldsdk\\plugins\\wwise\\thirdparty\\include\\ak\\wwiseauthoringapi\\akvariantbase.h",
            "c:\\program files\\microsoft visual studio\\2022\\community\\vc\\tools\\msvc\\14.33.31629\\include\\string_view",
            "d:\\palworldsdk\\plugins\\wwise\\thirdparty\\include\\ak\\wwiseauthoringapi\\akguid.h",
            "c:\\program files\\microsoft visual studio\\2022\\community\\vc\\tools\\msvc\\14.33.31629\\include\\locale",
            "c:\\program files\\microsoft visual studio\\2022\\community\\vc\\tools\\msvc\\14.33.31629\\include\\xlocbuf",
            "c:\\program files\\microsoft visual studio\\2022\\community\\vc\\tools\\msvc\\14.33.31629\\include\\xlocmes",
            "c:\\program files\\microsoft visual studio\\2022\\community\\vc\\tools\\msvc\\14.33.31629\\include\\xlocmon",
            "c:\\program files\\microsoft visual studio\\2022\\community\\vc\\tools\\msvc\\14.33.31629\\include\\xloctime",
            "c:\\program files\\microsoft visual studio\\2022\\community\\vc\\tools\\msvc\\14.33.31629\\include\\codecvt",
            "d:\\palworldsdk\\plugins\\wwise\\thirdparty\\include\\ak\\wwiseauthoringapi\\akautobahn\\akjson.h",
            "d:\\palworldsdk\\plugins\\wwise\\thirdparty\\include\\ak\\wwiseauthoringapi\\akjsonbase.h",
            "d:\\palworldsdk\\plugins\\wwise\\thirdparty\\include\\ak\\wwiseauthoringapi\\akautobahn\\jsonprovider.h",
            "d:\\palworldsdk\\plugins\\wwise\\thirdparty\\include\\ak\\wwiseauthoringapi\\akautobahn\\iwebsocketclienthandler.h",
            "d:\\palworldsdk\\plugins\\wwise\\thirdparty\\include\\ak\\wwiseauthoringapi\\akautobahn\\websocketclient.h",
            "d:\\palworldsdk\\plugins\\wwise\\thirdparty\\include\\ak\\wwiseauthoringapi\\akautobahn\\futureutils.h",
            "d:\\palworldsdk\\plugins\\wwise\\source\\akaudio\\private\\akwaapislate\\widgets\\input\\aksslider.cpp",
            "d:\\palworldsdk\\plugins\\wwise\\source\\akaudio\\classes\\akwaapislate\\widgets\\input\\aksslider.h",
            "d:\\ue_5.1\\engine\\source\\runtime\\slate\\public\\widgets\\input\\sslider.h",
            "d:\\palworldsdk\\plugins\\wwise\\source\\akaudio\\classes\\waapipicker\\swaapipicker.h",
            "d:\\palworldsdk\\plugins\\wwise\\source\\akaudio\\classes\\akwaapiumg\\components\\wwiseumgdragdropop.h",
            "d:\\palworldsdk\\plugins\\wwise\\source\\akaudio\\classes\\akwaapiumg\\components\\wwisepropertydragdropop.h",
            "d:\\ue_5.1\\engine\\source\\runtime\\slate\\public\\widgets\\input\\snumericentrybox.h",
            "d:\\ue_5.1\\engine\\source\\runtime\\slate\\public\\widgets\\input\\sspinbox.h",
            "d:\\ue_5.1\\engine\\source\\runtime\\slate\\public\\widgets\\colors\\scolorblock.h",
            "d:\\palworldsdk\\plugins\\wwise\\source\\akaudio\\private\\akwaapiumg\\components\\akboolpropertytocontrolcustomization.cpp",
            "d:\\palworldsdk\\plugins\\wwise\\source\\akaudio\\classes\\akwaapiumg\\components\\akboolpropertytocontrolcustomization.h",
            "d:\\palworldsdk\\plugins\\wwise\\source\\akaudio\\classes\\akwaapiumg\\components\\sakitemboolproperties.h",
            "d:\\palworldsdk\\plugins\\wwise\\source\\akaudio\\private\\akwaapiumg\\components\\akcheckbox.cpp",
            "d:\\palworldsdk\\plugins\\wwise\\source\\akaudio\\classes\\akwaapiumg\\components\\akcheckbox.h",
            "d:\\ue_5.1\\engine\\source\\runtime\\umg\\public\\components\\contentwidget.h",
            "d:\\ue_5.1\\engine\\source\\runtime\\umg\\public\\components\\panelwidget.h",
            "d:\\ue_5.1\\engine\\source\\runtime\\umg\\public\\components\\panelslot.h",
            "d:\\ue_5.1\\engine\\source\\runtime\\umg\\public\\components\\visual.h",
            "d:\\ue_5.1\\engine\\intermediate\\build\\win64\\unrealeditor\\inc\\umg\\uht\\visual.generated.h",
            "d:\\ue_5.1\\engine\\intermediate\\build\\win64\\unrealeditor\\inc\\umg\\uht\\panelslot.generated.h",
            "d:\\ue_5.1\\engine\\source\\runtime\\umg\\public\\components\\widget.h",
            "d:\\ue_5.1\\engine\\source\\runtime\\umg\\public\\fieldnotification\\fieldnotificationdeclaration.h",
            "d:\\ue_5.1\\engine\\source\\runtime\\umg\\public\\fieldnotification\\fieldid.h",
            "d:\\ue_5.1\\engine\\source\\runtime\\umg\\public\\fieldnotification\\fieldvariant.h",
            "d:\\ue_5.1\\engine\\intermediate\\build\\win64\\unrealeditor\\inc\\umg\\uht\\fieldid.generated.h",
            "d:\\ue_5.1\\engine\\source\\runtime\\umg\\public\\fieldnotification\\iclassdescriptor.h",
            "d:\\ue_5.1\\engine\\source\\runtime\\umg\\public\\fieldnotification\\ifieldvaluechanged.h",
            "d:\\ue_5.1\\engine\\intermediate\\build\\win64\\unrealeditor\\inc\\umg\\uht\\ifieldvaluechanged.generated.h",
            "d:\\ue_5.1\\engine\\source\\runtime\\umg\\public\\slate\\widgettransform.h",
            "d:\\ue_5.1\\engine\\intermediate\\build\\win64\\unrealeditor\\inc\\umg\\uht\\widgettransform.generated.h",
            "d:\\ue_5.1\\engine\\source\\runtime\\engine\\classes\\gameframework\\playercontroller.h",
            "d:\\ue_5.1\\engine\\source\\runtime\\engine\\classes\\gameframework\\playermutelist.h",
            "d:\\ue_5.1\\engine\\intermediate\\build\\win64\\unrealeditor\\inc\\engine\\uht\\playermutelist.generated.h",
            "d:\\ue_5.1\\engine\\source\\runtime\\engine\\classes\\camera\\playercameramanager.h",
            "d:\\ue_5.1\\engine\\intermediate\\build\\win64\\unrealeditor\\inc\\engine\\uht\\playercameramanager.generated.h",
            "d:\\ue_5.1\\engine\\source\\runtime\\engine\\classes\\components\\inputcomponent.h",
            "d:\\ue_5.1\\engine\\intermediate\\build\\win64\\unrealeditor\\inc\\engine\\uht\\inputcomponent.generated.h",
            "d:\\ue_5.1\\engine\\source\\runtime\\engine\\classes\\gameframework\\forcefeedbackeffect.h",
            "d:\\ue_5.1\\engine\\intermediate\\build\\win64\\unrealeditor\\inc\\engine\\uht\\forcefeedbackeffect.generated.h",
            "d:\\ue_5.1\\engine\\source\\runtime\\applicationcore\\public\\genericplatform\\iinputinterface.h",
            "d:\\ue_5.1\\engine\\source\\runtime\\engine\\classes\\gameframework\\playerinput.h",
            "d:\\ue_5.1\\engine\\source\\runtime\\engine\\public\\gesturerecognizer.h",
            "d:\\ue_5.1\\engine\\source\\runtime\\engine\\public\\keystate.h",
            "d:\\ue_5.1\\engine\\intermediate\\build\\win64\\unrealeditor\\inc\\engine\\uht\\playerinput.generated.h",
            "d:\\ue_5.1\\engine\\source\\runtime\\engine\\public\\physics\\asyncphysicsdata.h",
            "d:\\ue_5.1\\engine\\intermediate\\build\\win64\\unrealeditor\\inc\\engine\\uht\\asyncphysicsdata.generated.h",
            "d:\\ue_5.1\\engine\\source\\runtime\\engine\\public\\worldpartition\\worldpartitionstreamingsource.h",
            "d:\\ue_5.1\\engine\\intermediate\\build\\win64\\unrealeditor\\inc\\engine\\uht\\worldpartitionstreamingsource.generated.h",
            "d:\\ue_5.1\\engine\\intermediate\\build\\win64\\unrealeditor\\inc\\engine\\uht\\playercontroller.generated.h",
            "d:\\ue_5.1\\engine\\source\\runtime\\umg\\public\\blueprint\\widgetnavigation.h",
            "d:\\ue_5.1\\engine\\source\\runtime\\slatecore\\public\\types\\navigationmetadata.h",
            "d:\\ue_5.1\\engine\\intermediate\\build\\win64\\unrealeditor\\inc\\umg\\uht\\widgetnavigation.generated.h",
            "d:\\ue_5.1\\engine\\intermediate\\build\\win64\\unrealeditor\\inc\\umg\\uht\\widget.generated.h",
            "d:\\ue_5.1\\engine\\source\\runtime\\umg\\public\\blueprint\\userwidget.h",
            "d:\\ue_5.1\\engine\\source\\runtime\\coreuobject\\public\\uobject\\objectsavecontext.h",
            "d:\\ue_5.1\\engine\\source\\runtime\\umg\\public\\components\\namedslotinterface.h",
            "d:\\ue_5.1\\engine\\intermediate\\build\\win64\\unrealeditor\\inc\\umg\\uht\\namedslotinterface.generated.h",
            "d:\\ue_5.1\\engine\\source\\runtime\\engine\\classes\\engine\\localplayer.h",
            "d:\\ue_5.1\\engine\\source\\runtime\\engine\\classes\\engine\\player.h",
            "d:\\ue_5.1\\engine\\intermediate\\build\\win64\\unrealeditor\\inc\\engine\\uht\\player.generated.h",
            "d:\\ue_5.1\\engine\\source\\runtime\\engine\\public\\subsystems\\localplayersubsystem.h",
            "d:\\ue_5.1\\engine\\intermediate\\build\\win64\\unrealeditor\\inc\\engine\\uht\\localplayersubsystem.generated.h",
            "d:\\ue_5.1\\engine\\intermediate\\build\\win64\\unrealeditor\\inc\\engine\\uht\\localplayer.generated.h",
            "d:\\ue_5.1\\engine\\source\\runtime\\slate\\public\\widgets\\layout\\anchors.h",
            "d:\\ue_5.1\\engine\\intermediate\\build\\win64\\unrealeditor\\inc\\slate\\uht\\anchors.generated.h",
            "d:\\ue_5.1\\engine\\source\\runtime\\umg\\public\\animation\\widgetanimationevents.h",
            "d:\\ue_5.1\\engine\\intermediate\\build\\win64\\unrealeditor\\inc\\umg\\uht\\widgetanimationevents.generated.h",
            "d:\\ue_5.1\\engine\\source\\runtime\\umg\\public\\blueprint\\widgetblueprintgeneratedclass.h",
            "d:\\ue_5.1\\engine\\source\\runtime\\umg\\public\\binding\\dynamicpropertypath.h",
            "d:\\ue_5.1\\engine\\source\\runtime\\propertypath\\public\\propertypathhelpers.h",
            "d:\\ue_5.1\\engine\\source\\runtime\\propertypath\\public\\propertytypecompatibility.h",
            "d:\\ue_5.1\\engine\\intermediate\\build\\win64\\unrealeditor\\inc\\propertypath\\uht\\propertypathhelpers.generated.h",
            "d:\\ue_5.1\\engine\\intermediate\\build\\win64\\unrealeditor\\inc\\umg\\uht\\dynamicpropertypath.generated.h",
            "d:\\ue_5.1\\engine\\intermediate\\build\\win64\\unrealeditor\\inc\\umg\\uht\\widgetblueprintgeneratedclass.generated.h",
            "d:\\ue_5.1\\engine\\intermediate\\build\\win64\\unrealeditor\\inc\\umg\\uht\\userwidget.generated.h",
            "d:\\ue_5.1\\engine\\intermediate\\build\\win64\\unrealeditor\\inc\\umg\\uht\\panelwidget.generated.h",
            "d:\\ue_5.1\\engine\\intermediate\\build\\win64\\unrealeditor\\inc\\umg\\uht\\contentwidget.generated.h",
            "d:\\palworldsdk\\plugins\\wwise\\source\\akaudio\\classes\\akwaapiumg\\components\\akslider.h",
            "d:\\palworldsdk\\plugins\\wwise\\source\\akaudio\\classes\\akwaapiumg\\components\\akitemproperties.h",
            "d:\\palworldsdk\\plugins\\wwise\\source\\akaudio\\classes\\akwaapiumg\\components\\sakitemproperties.h",
            "d:\\palworldsdk\\plugins\\wwise\\intermediate\\build\\win64\\unrealeditor\\inc\\akaudio\\uht\\akitemproperties.generated.h",
            "d:\\palworldsdk\\plugins\\wwise\\intermediate\\build\\win64\\unrealeditor\\inc\\akaudio\\uht\\akslider.generated.h",
            "d:\\palworldsdk\\plugins\\wwise\\source\\akaudio\\classes\\akwaapiumg\\components\\akitemboolproperties.h",
            "d:\\palworldsdk\\plugins\\wwise\\intermediate\\build\\win64\\unrealeditor\\inc\\akaudio\\uht\\akitemboolproperties.generated.h",
            "d:\\palworldsdk\\plugins\\wwise\\intermediate\\build\\win64\\unrealeditor\\inc\\akaudio\\uht\\akcheckbox.generated.h",
            "d:\\ue_5.1\\engine\\source\\runtime\\engine\\classes\\slate\\slatebrushasset.h",
            "d:\\ue_5.1\\engine\\intermediate\\build\\win64\\unrealeditor\\inc\\engine\\uht\\slatebrushasset.generated.h",
            "d:\\palworldsdk\\plugins\\wwise\\source\\akaudio\\classes\\akwaapiumg\\components\\wwiseboolpropertydragdropop.h",
            "d:\\palworldsdk\\plugins\\wwise\\source\\akaudio\\private\\akwaapiumg\\components\\akitemboolproperties.cpp",
            "d:\\palworldsdk\\plugins\\wwise\\source\\akaudio\\private\\akwaapiumg\\components\\akitemproperties.cpp",
            "d:\\palworldsdk\\plugins\\wwise\\source\\akaudio\\private\\akwaapiumg\\components\\akpropertytocontrolcustomization.cpp",
            "d:\\palworldsdk\\plugins\\wwise\\source\\akaudio\\classes\\akwaapiumg\\components\\akpropertytocontrolcustomization.h",
            "d:\\palworldsdk\\plugins\\wwise\\source\\akaudio\\private\\akwaapiumg\\components\\akslider.cpp",
            "d:\\ue_5.1\\engine\\source\\runtime\\umg\\public\\umgstyle.h",
            "d:\\ue_5.1\\engine\\source\\runtime\\slatecore\\public\\styling\\slatestyle.h",
            "d:\\ue_5.1\\engine\\source\\runtime\\slatecore\\public\\brushes\\slateborderbrush.h",
            "d:\\ue_5.1\\engine\\source\\runtime\\slatecore\\public\\brushes\\slateboxbrush.h",
            "d:\\ue_5.1\\engine\\source\\runtime\\slatecore\\public\\brushes\\slatecolorbrush.h",
            "d:\\ue_5.1\\engine\\source\\runtime\\slatecore\\public\\brushes\\slateroundedboxbrush.h",
            "d:\\ue_5.1\\engine\\source\\runtime\\slatecore\\public\\brushes\\slateimagebrush.h",
            "d:\\palworldsdk\\plugins\\wwise\\source\\akaudio\\classes\\akwaapiumg\\components\\akwwiseobjectdetailsstructcustomization.h"
        ],
        "ImportedModules": [],
        "ImportedHeaderUnits": []
    }
}